pylogic/__init__.py
pylogic/common_defs.py
pylogic/fol.py
pylogic/propositional.py
python_logic-0.0.1.dist-info/LICENSE
python_logic-0.0.1.dist-info/METADATA
python_logic-0.0.1.dist-info/WHEEL
python_logic-0.0.1.dist-info/top_level.txt
python_logic-0.0.1.dist-info/RECORD
