Metadata-Version: 2.1
Name: python-logic
Version: 0.0.1
Summary: A package to run logic inferences on python
Author-email: Diego Palma <dpalmasan@gmail.com>
Project-URL: Homepage, https://github.com/dpalmasan/py-logic
Project-URL: Issues, https://github.com/dpalmasan/py-logic/issues
Classifier: Programming Language :: Python :: 3
Classifier: License :: OSI Approved :: MIT License
Classifier: Operating System :: OS Independent
Requires-Python: >=3.8
License-File: LICENSE
